{
    "Items": [
        {
            "Name": "Antidote",
            "Description": "Immediately heals Poison",
            "Cost": "6"
        },
        {
            "Name": "Bandage",
            "Description": "Immediately heals Bleed",
            "Cost": "6"
        },
        {
            "Name": "Basic Weapon",
            "Description": "Basic type of any weapon (no modifiers)",
            "Cost": "5"
        },
        {
            "Name": "Brain Boost",
            "Description": "+2 to next Deduction Roll",
            "Cost": "15"
        },
        {
            "Name": "Brawl Balm",
            "Description": "+2 to next Melee Roll",
            "Cost": "15"
        },
        {
            "Name": "Brew",
            "Description": "Immediately heals Scared",
            "Cost": "6"
        },
        {
            "Name": "Concentration",
            "Description": "+2 to next Shoot Roll",
            "Cost": "15"
        },
        {
            "Name": "Concoction",
            "Description": "Heals 10 SP",
            "Cost": "10"
        },
        {
            "Name": "Concoction+",
            "Description": "Heals all SP",
            "Cost": "25"
        },
        {
            "Name": "Confidence Booster",
            "Description": "+2 to next Diplomacy Roll",
            "Cost": "15"
        },
        {
            "Name": "Dangerous Mushroom",
            "Description": "Requires a resilience roll:\r\n-\tSuccess: Heal 1d6 HP\r\n-\tMinor Success: Heal 1d6 HP but gain Poison\r\n-\tFail: Gain Poison",
            "Cost": "5"
        },
        {
            "Name": "Elbow Grease",
            "Description": "+2 to next Tinker Roll",
            "Cost": "15"
        },
        {
            "Name": "Encyclopedia Light",
            "Description": "+2 to next Knowledge Roll",
            "Cost": "15"
        },
        {
            "Name": "Energy Boost",
            "Description": "+2 to next Energy Roll",
            "Cost": "15"
        },
        {
            "Name": "Enhancer",
            "Description": "+2 to next Sense Roll",
            "Cost": "15"
        },
        {
            "Name": "Eye Drop",
            "Description": "Immediately heals Blind",
            "Cost": "6"
        },
        {
            "Name": "Flex",
            "Description": "+2 to next Movement Roll",
            "Cost": "15"
        },
        {
            "Name": "Lazarus Tonic",
            "Description": "Revives a fainted comrade in battle",
            "Cost": "100"
        },
        {
            "Name": "Magnifier",
            "Description": "+2 to next Search Roll",
            "Cost": "15"
        },
        {
            "Name": "Medication",
            "Description": "Immediately heals Mania",
            "Cost": "6"
        },
        {
            "Name": "Medicine",
            "Description": "Heals 2d10 HP, but can only be used outside of battle",
            "Cost": "7"
        },
        {
            "Name": "Ointment",
            "Description": "Immediately heals Burn",
            "Cost": "6"
        },
        {
            "Name": "Potion",
            "Description": "Heals 10 HP",
            "Cost": "10"
        },
        {
            "Name": "Potion+",
            "Description": "Heals All HP",
            "Cost": "25"
        },
        {
            "Name": "Scale Armor",
            "Description": "Adds +2 Armor",
            "Cost": "10"
        },
        {
            "Name": "Steroid",
            "Description": "+2 to next Brawn Roll",
            "Cost": "15"
        },
        {
            "Name": "Tincture",
            "Description": "Heals 1d10 HP and 1d10 SP",
            "Cost": "30"
        },
        {
            "Name": "Tincture+",
            "Description": "Heals all HP and SP",
            "Cost": "70"
        },
        {
            "Name": "Vitamin",
            "Description": "+2 to next Resilience Roll",
            "Cost": "15"
        },
        {
            "Name": "Welder's Gloves",
            "Description": "Gloves that add +2 to Tinker",
            "Cost": "22"
        },
        {
            "Name": "Basic Armor",
            "Description": "Adds +2 Armor",
            "Cost": "10"
        },
        {
            "Name": "Jerky",
            "Description": "Restore 3 SP",
            "Cost": "3"
        },
        {
            "Name": "Rock Grenade",
            "Description": "A grenade that does 1d6 Earth damage",
            "Cost": "6"
        },
        {
            "Name": "Aqua Grenade",
            "Description": "A grenade that does 1d6 Water damage",
            "Cost": "6"
        },
        {
            "Name": "Wind Grenade",
            "Description": "A grenade that does 1d6 Air damage",
            "Cost": "6"
        },
        {
            "Name": "Shock Grenade",
            "Description": "A grenade that does 1d6 Lightning damage",
            "Cost": "6"
        },
        {
            "Name": "Flame Grenade",
            "Description": "A grenade that does 1d6 Fire damage",
            "Cost": "6"
        },
        {
            "Name": "Frost Grenade",
            "Description": "A grenade that does 1d6 Ice damage",
            "Cost": "6"
        },
        {
            "Name": "Evil Grenade",
            "Description": "A grenade that does 1d6 Dark damage",
            "Cost": "6"
        },
        {
            "Name": "Saintly Grenade",
            "Description": "A grenade that does 1d6 Holy damage",
            "Cost": "6"
        },
        {
            "Name": "Basic Airship",
            "Description": "An airship with a capacity of 13.  Not very good for combat.",
            "Cost": "700"
        }
    ],
    "Bestiary": [
        {
            "Name": "Armored Rhino",
            "Description": "A rhinoceros with a thick metal hide",
            "HP": "10",
            "Armor": "5",
            "Immunity": "None",
            "Locations": "Plains",
            "Weakness": "Fire, Lightning",
            "Attacks": "Charge: 1d12 damage\r\n\r\nGround Stomp: 1d8 damage to 2 enemies"
        },
        {
            "Name": "Baterina",
            "Description": "A giant back with legs that wears a tutu",
            "HP": "6",
            "Armor": "0",
            "Immunity": "None",
            "Locations": "Cave",
            "Weakness": "Holy",
            "Attacks": "Bite: 1d12 damage.  Causes Mania"
        },
        {
            "Name": "Brown Dragon",
            "Description": "Dragons the size of human beings with thick brown scales",
            "HP": "10",
            "Armor": "2",
            "Immunity": "Earth",
            "Locations": "Sky, Cave, Mountain",
            "Weakness": "Air",
            "Attacks": "Scratch: 1d8+3 damage\r\n\r\nBite: 1d8 damage.  Will latch onto a character causing the following: -1 to Movement Rolls and automatic 1d4 damage until free\r\n\r\nDirt Tail Whip: 1d6 ranged Earth damage plus causes Blind."
        },
        {
            "Name": "Crystal Squid",
            "Description": "A squid that can swim",
            "HP": "13",
            "Armor": "1",
            "Immunity": "Water",
            "Locations": "Underwater, Shore",
            "Weakness": "Lightning",
            "Attacks": "Snap: 1d10 damage to a single player\r\n\r\nEmbrace: 1d4 damage.  Traps the player who must make a move to escape\r\n\r\nWater Jet: 1d10 damage to all players"
        },
        {
            "Name": "Dark Wolf",
            "Description": "A tall wolf with charcoal-like skin",
            "HP": "9",
            "Armor": "0",
            "Immunity": "Dark",
            "Locations": "Cave, Forest",
            "Weakness": "Holy",
            "Attacks": "Bite: 1d10 damage"
        },
        {
            "Name": "Electric Eel",
            "Description": "An underwater creature that shoots electricity",
            "HP": "9",
            "Armor": "0",
            "Immunity": "None",
            "Locations": "Underwater",
            "Weakness": "None",
            "Attacks": "Bite: 1d10 damage\r\n\r\nShock: 1d8 Lightning damage to all enemies.  Causes Paralysis."
        },
        {
            "Name": "Experiment",
            "Description": "A person that has been experimented on and no longer looks human.  Arms have been replaced with guns",
            "HP": "9",
            "Armor": "0",
            "Immunity": "None",
            "Locations": "Swamp, Cave, City",
            "Weakness": "None",
            "Attacks": "Manic Shot: 1d8 -1 damage.  Causes mania"
        },
        {
            "Name": "Fire Scorpion",
            "Description": "A big scorpion that has does fire damage",
            "HP": "14",
            "Armor": "7",
            "Immunity": "Fire",
            "Locations": "Desert",
            "Weakness": "Ice",
            "Attacks": "Sting: 1d12 fire damage.  Causes burn.\r\n\r\nPinch: 1d4.  Traps the player who must make a move to escape."
        },
        {
            "Name": "Flying Drone",
            "Description": "A robot in the air that can shoot an enemy",
            "HP": "10",
            "Armor": "1",
            "Immunity": "None",
            "Locations": "Sky, City",
            "Weakness": "Lightning",
            "Attacks": "Laser Shot: 1d6 damage"
        },
        {
            "Name": "Giant Weasel",
            "Description": "A giant weasel",
            "HP": "11",
            "Armor": "0",
            "Immunity": "None",
            "Locations": "Forest, Plains",
            "Weakness": "None",
            "Attacks": "Attack: 1d6 damage"
        },
        {
            "Name": "Gunner Soldier",
            "Description": "A soldier with a gun",
            "HP": "7",
            "Armor": "4",
            "Locations": "City",
            "Weakness": "None",
            "Attacks": "Gunshot: 1d10 damage to an enemy\r\n\r\nGun Spray: 1d4 damage to all enemies"
        },
        {
            "Name": "Hornet Swarm",
            "Description": "A swarm of stinging hornets",
            "HP": "5",
            "Armor": "0",
            "Immunity": "None",
            "Locations": "Forest, Plains, Desert",
            "Weakness": "Fire",
            "Attacks": "Venomous Sting: 1d4+1 damage to all enemies.  Causes Poison."
        },
        {
            "Name": "Magmus",
            "Description": "A humanoid creature made of lava rock",
            "HP": "7",
            "Armor": "2",
            "Immunity": "Fire",
            "Locations": "Cave, Mountain",
            "Weakness": "Ice",
            "Attacks": "Fire Punch: 1d8 Fire damage."
        },
        {
            "Name": "Marionette",
            "Description": "A marionette.  A puppet on strings.",
            "HP": "6",
            "Armor": "0",
            "Immunity": "None",
            "Locations": "City",
            "Weakness": "Fire",
            "Attacks": "Slap: 1d8 damage"
        },
        {
            "Name": "Mollusk",
            "Description": "A creature with an oyster-like body, lobster legs, and pincers",
            "HP": "3",
            "Armor": "4",
            "Immunity": "Water",
            "Locations": "Shore, Underwater",
            "Weakness": "Lightning",
            "Attacks": "Clamp: 1d8+1 damage"
        },
        {
            "Name": "Muskroom",
            "Description": "A muskrat covered in mushrooms",
            "HP": "3",
            "Armor": "0",
            "Immunity": "None",
            "Locations": "Cave, Forest",
            "Weakness": "Fire",
            "Attacks": "Scratch: 1d4+3 damage\r\n\r\nBite: 1d4 damage.  Causes Poison.\r\n\r\nSpore Cloud: Cause Poison on all enemies"
        },
        {
            "Name": "Ring of Fire",
            "Description": "A literal floating circle of fire",
            "HP": "7",
            "Armor": "0",
            "Immunity": "Fire",
            "Locations": "Cave, Mountain",
            "Weakness": "Ice",
            "Attacks": "Fireball: 1d8 fire damage.  Causes Burn."
        },
        {
            "Name": "Ring of Lightning",
            "Description": "A literal floating circle of electricity",
            "HP": "7",
            "Armor": "0",
            "Immunity": "Lightning",
            "Locations": "Cave, Mountain",
            "Weakness": "Water",
            "Attacks": "Lightning Strike: 1d8 Lightning damage.  Causes Paralysis."
        },
        {
            "Name": "Rock Beast",
            "Description": "A humanoid creature made of dirt and rock",
            "HP": "17",
            "Armor": "3",
            "Immunity": "Earth",
            "Locations": "Plains, Cave, Mountain",
            "Weakness": "Air",
            "Attacks": "Rock Punch: 1d10 Earth damage\r\n\r\nGrab: Entrap an enemy"
        },
        {
            "Name": "Skeleton Knight",
            "Description": "A skeleton in armor with a sword",
            "HP": "5",
            "Armor": "4",
            "Immunity": "Dark",
            "Locations": "Cave, Swamp",
            "Weakness": "Holy",
            "Attacks": "Slash: 1d8 damage"
        },
        {
            "Name": "Snow Vixen",
            "Description": "A giant white fox",
            "HP": "11",
            "Armor": "0",
            "Immunity": "Ice",
            "Locations": "Tundra, Forest",
            "Weakness": "Fire",
            "Attacks": "Bite: 1d10 damage\r\n\r\nScratch: 1d6 damage\r\n\r\nSnow Beam: 1d10 Ice damage"
        },
        {
            "Name": "Walking Shark",
            "Description": "A shark on two legs",
            "HP": "9",
            "Armor": "0",
            "Immunity": "Water",
            "Locations": "Shore",
            "Weakness": "Lightning",
            "Attacks": "Bite: 1d10 damage.  Once bitten, 3 damage every turn until the enemy escapes."
        },
        {
            "Name": "Waterbone",
            "Description": "A skeleton inside a bubble of water",
            "HP": "9",
            "Armor": "1",
            "Immunity": "Water",
            "Locations": "Underwater",
            "Weakness": "Holy, Lightning",
            "Attacks": "Bubble Attack: 1d10 Water damage\r\n\r\nBone Attack: 1d12 Dark damage."
        },
        {
            "Name": "Tortussle",
            "Description": "A giant tortoise with glowing eyes",
            "HP": "18",
            "Armor": "2",
            "Immunity": "Water",
            "Locations": "Underwater, Shore, Swamp, Forest, Plains",
            "Weakness": "Lightning",
            "Attacks": "Bite: 1d12+2 damage\r\n\r\n"
        }
    ],
    "Sample_Custom_Moves": [
        {
            "Name": "Big Ears",
            "Description": "+2 to Sense roll when listening to others' conversations"
        },
        {
            "Name": "Call of the Wild",
            "Description": "Spend 1 SP to summon a Wolf to your side if in a forest.  Wolf has 4 HP and can do 1d6 damage and has its own turn during combat."
        },
        {
            "Name": "Cavern Explorer",
            "Description": "+2 to Sense roll when inside a cave or cavern"
        },
        {
            "Name": "Chef",
            "Description": "+2 to Tinker for creating a delicious meal that will restore 1d4 HP or SP"
        },
        {
            "Name": "Detective",
            "Description": "+2 to Search when investigating a crime"
        },
        {
            "Name": "Informed Traveller",
            "Description": "+2 to Knowledge roll for information about a city/town you haven't been to before"
        },
        {
            "Name": "Inside your Mind",
            "Description": "Spend 10 SP to read somebody's mind.  Automatic success on any Diplomacy roll."
        },
        {
            "Name": "Mountain Climber",
            "Description": "+2 to Brawn roll for climbing mountains"
        },
        {
            "Name": "Prosecutor",
            "Description": "+2 to Diplomacy when you try to convince others that someone is lying (whether it's true or not)"
        },
        {
            "Name": "Brawler",
            "Description": "+2 to Melee when fighting one-on-one"
        },
        {
            "Name": "Good Shepherd",
            "Description": "+2 to Sense when attempting to wrangle a plant-eating animal"
        }
    ]
}